evap/__init__.py
evap/__main__.py
evap/context_processors.py
evap/middleware.py
evap/settings.py
evap/settings_test.py
evap/tools.py
evap/urls.py
evap/wsgi.py
evap/contributor/__init__.py
evap/contributor/forms.py
evap/contributor/urls.py
evap/contributor/views.py
evap/contributor/templates/contributor_evaluation_form.html
evap/contributor/templates/contributor_index.html
evap/contributor/tests/__init__.py
evap/contributor/tests/test_forms.py
evap/contributor/tests/test_live.py
evap/contributor/tests/test_views.py
evap/development/__init__.py
evap/development/localsettings.template.py
evap/development/manage_autocompletion.sh
evap/development/urls.py
evap/development/views.py
evap/development/fixtures/test_data.json
evap/development/fixtures/upload/grades/1525/test_results_01.txt
evap/development/fixtures/upload/grades/1577/test_results_03.txt
evap/development/fixtures/upload/grades/1694/test_results_02.txt
evap/development/management/__init__.py
evap/development/management/commands/__init__.py
evap/development/management/commands/dump_testdata.py
evap/development/management/commands/reload_testdata.py
evap/development/management/commands/run.py
evap/development/management/commands/translate.py
evap/development/templates/development_components.html
evap/development/tests/__init__.py
evap/development/tests/test_commands.py
evap/evaluation/__init__.py
evap/evaluation/auth.py
evap/evaluation/forms.py
evap/evaluation/middleware.py
evap/evaluation/models.py
evap/evaluation/models_logging.py
evap/evaluation/tools.py
evap/evaluation/urls.py
evap/evaluation/views.py
evap/evaluation/management/__init__.py
evap/evaluation/management/commands/__init__.py
evap/evaluation/management/commands/anonymize.py
evap/evaluation/management/commands/format.py
evap/evaluation/management/commands/import_cms_data.py
evap/evaluation/management/commands/lint.py
evap/evaluation/management/commands/loaddata_unlogged.py
evap/evaluation/management/commands/precommit.py
evap-2026.1.2.dist-info/METADATA
evap-2026.1.2.dist-info/WHEEL
evap-2026.1.2.dist-info/licenses/LICENSE.md
evap-2026.1.2.dist-info/RECORD
