Metadata-Version: 2.4
Name: evap
Version: 2026.1.2
Summary: EvaP
License-File: LICENSE.md
Requires-Python: >=3.11.0
Requires-Dist: django-extensions~=4.1.0
Requires-Dist: django-fsm-2~=4.1.0
Requires-Dist: django~=5.2.0
Requires-Dist: mozilla-django-oidc~=5.0.2
Requires-Dist: openpyxl~=3.1.5
Requires-Dist: psycopg~=3.3.2
Requires-Dist: pydantic~=2.12.5
Requires-Dist: redis~=7.1.0
Requires-Dist: requests~=2.32.4
Requires-Dist: typing-extensions~=4.15.0
Requires-Dist: xlwt~=1.3.0
Provides-Extra: psycopg-binary
Requires-Dist: psycopg[binary]; extra == 'psycopg-binary'
Provides-Extra: psycopg-c
Requires-Dist: psycopg[c]; extra == 'psycopg-c'
